agwui/ExtraType.py
agwui/FunctionDefinition.py
agwui/FunctionEntrypoint.py
agwui/FunctionParameter.py
agwui/Injector.py
agwui/__init__.py
agwui/class_handler.py
agwui/class_injector.py
agwui/function_extractor.py
agwui/function_injector.py
agwui/get_function_injector.py
agwui/get_schema_function_injector.py
agwui/index_class_handler.py
agwui/inspect_test.py
agwui/path_builder.py
agwui/post_function_injector.py
agwui/templates/class.html
agwui/templates/function.html
agwui/templates/preview_image.html
agwui-0.0.6.dist-info/METADATA
agwui-0.0.6.dist-info/WHEEL
agwui-0.0.6.dist-info/top_level.txt
agwui-0.0.6.dist-info/RECORD
